purpleair_data_logger/PurpleAirCSVDataLogger.py
purpleair_data_logger/PurpleAirCSVDataLoggerConstants.py
purpleair_data_logger/PurpleAirDataLogger.py
purpleair_data_logger/PurpleAirDataLoggerHelpers.py
purpleair_data_logger/PurpleAirPSQLDataLogger.py
purpleair_data_logger/PurpleAirPSQLQueryStatements.py
purpleair_data_logger/PurpleAirSQLiteDataLogger.py
purpleair_data_logger/PurpleAirSQLiteQueryStatements.py
purpleair_data_logger/__init__.py
purpleair_data_logger-1.4.0.dist-info/LICENSE
purpleair_data_logger-1.4.0.dist-info/METADATA
purpleair_data_logger-1.4.0.dist-info/WHEEL
purpleair_data_logger-1.4.0.dist-info/top_level.txt
purpleair_data_logger-1.4.0.dist-info/RECORD
