Metadata-Version: 2.2
Name: purpleair_data_logger
Version: 1.4.0
Home-page: https://github.com/carlkidcrypto/purpleair_data_logger
Author: Carlos Santos
Author-email: dose.lucky.sake@cloak.id
License: MIT
Keywords: purpleair_data_logger,purple air,purple air data logger,PurpleAirPSQLDataLogger,PurpleAirCSVDataLogger,purple air api,PurpleAirSQLiteDataLogger
Platform: Windows 32/64
Platform: Linux 32/64
Platform: MacOS 32/64
Requires-Python: <3.14,>=3.9
License-File: LICENSE
Requires-Dist: pg8000==1.31.2
Requires-Dist: requests
Requires-Dist: purpleair_api==1.2.0
